vit_flax/__init__.py
vit_flax/layers.py
vit_flax/vit.py
vit_flax-0.0.3.dist-info/LICENSE
vit_flax-0.0.3.dist-info/METADATA
vit_flax-0.0.3.dist-info/WHEEL
vit_flax-0.0.3.dist-info/top_level.txt
vit_flax-0.0.3.dist-info/RECORD
