Metadata-Version: 2.1
Name: vit-flax
Version: 0.0.3
Summary: Vision Transformer, ViT - Flax
Home-page: https://github.com/vballoli/vit-flax
Author: Vaibhav Balloli
Author-email: balloli.vb@gmail.com
License: MIT
Keywords: computer vision,transformers,flax,jax,transformers in computer vision
Platform: UNKNOWN
Classifier: Development Status :: 4 - Beta
Classifier: Intended Audience :: Developers
Classifier: Topic :: Scientific/Engineering :: Artificial Intelligence
Classifier: License :: OSI Approved :: MIT License
Classifier: Programming Language :: Python :: 3.6
Requires-Dist: jax
Requires-Dist: jaxlib
Requires-Dist: flax
